<?xml version="1.0" encoding="UTF-8"?>
<messages name="ServerMsg" lang="CN_FIRST">
<message mid="2"><![CDATA[the wrong user name or password]]></message>
<message mid="3"><![CDATA[unable to confirm the error]]></message>
<message mid="4"><![CDATA[can not repeat the landing]]></message>
<message mid="5"><![CDATA[repeat login account]]></message>
<message mid="6"><![CDATA[can not find this user]]></message>
<message mid="7"><![CDATA[not connected with the database]]></message>
<message mid="8"><![CDATA[and the server connection is not smooth]]></message>
<message mid="9"><![CDATA[and the server connection is not smooth]]></message>
<message mid="100"><![CDATA[login error]]></message>
<message mid="101"><![CDATA[version does not match]]></message>
<message mid="102"><![CDATA[account number or password error]]></message>
<message mid="103"><![CDATA[Please select a server]]></message>
<message mid="104"><![CDATA[Select the role]]></message>
<message mid="105"><![CDATA[Please Select Channel]]></message>
<message mid="106"><![CDATA[role name already exists]]></message>
<message mid="107"><![CDATA[complete role of the deleted]]></message>
<message mid="108"><![CDATA[Sign repeat]]></message>
<message mid="109"><![CDATA[Could not get the role of information]]></message>
<message mid="110"><![CDATA[unable to generate role]]></message>
<message mid="111"><![CDATA[role of the components space]]></message>
<message mid="112"><![CDATA[role of the code does not match]]></message>
<message mid="113"><![CDATA[character a failed]]></message>
<message mid="200"><![CDATA[no corresponding shortcut bar]]></message>
<message mid="300"><![CDATA[team build failed]]></message>
<message mid="301"><![CDATA[delete team failed]]></message>
<message mid="302"><![CDATA[can not join the team]]></message>
<message mid="303"><![CDATA[World regional level is low, can not join the ranks]]></message>
<message mid="304"><![CDATA[character level is too low, not invited to team up]]></message>
<message mid="305"><![CDATA[password error, can not join the ranks]]></message>
<message mid="306"><![CDATA[can not quit team]]></message>
<message mid="307"><![CDATA[can not start the game]]></message>
<message mid="308"><![CDATA[invitation to failure.]]></message>
<message mid="309"><![CDATA[the other party has already belong to other teams]]></message>
<message mid="310"><![CDATA[the other regions of the world level is too low, not invited to team up]]></message>
<message mid="311"><![CDATA[the other character level is too low, not invited to team up]]></message>
<message mid="312"><![CDATA[is the role of invited]]></message>
<message mid="313"><![CDATA[invited players does not exist.]]></message>
<message mid="314"><![CDATA[In addition to team members kick failed]]></message>
<message mid="315"><![CDATA[designated team captain failed]]></message>
<message mid="316"><![CDATA[transfer channel failed]]></message>
<message mid="400"><![CDATA[Articles error]]></message>
<message mid="401"><![CDATA[non-existent goods]]></message>
<message mid="402"><![CDATA[item code does not match]]></message>
<message mid="403"><![CDATA[item position error]]></message>
<message mid="404"><![CDATA[the number of items over]]></message>
<message mid="405"><![CDATA[article space]]></message>
<message mid="406"><![CDATA[no overlapping items]]></message>
<message mid="407"><![CDATA[there is the same code items]]></message>
<message mid="408"><![CDATA[the lack of gold]]></message>
<message mid="409"><![CDATA[bound items]]></message>
<message mid="410"><![CDATA[heraldry combination failed]]></message>
<message mid="411"><![CDATA[gem update failed]]></message>
<message mid="500"><![CDATA[store does not exist]]></message>
<message mid="501"><![CDATA[Select the items do not exist]]></message>
<message mid="502"><![CDATA[non-store items]]></message>
<message mid="503"><![CDATA[coin shortage]]></message>
<message mid="504"><![CDATA[add items failed]]></message>
<message mid="505"><![CDATA[recipient does not exist]]></message>
<message mid="506"><![CDATA[message have items]]></message>
<message mid="507"><![CDATA[Mail No items]]></message>
<message mid="508"><![CDATA[no longer registered to the store]]></message>
<message mid="509"><![CDATA[There are no registered articles]]></message>
<message mid="510"><![CDATA[items have been sold]]></message>
<message mid="511"><![CDATA[not to sell items]]></message>
<message mid="512"><![CDATA[There are no transaction object]]></message>
<message mid="513"><![CDATA[Transaction failed]]></message>
<message mid="514"><![CDATA[can not send messages to yourself]]></message>
<message mid="600"><![CDATA[task delete failed]]></message>
<message mid="601"><![CDATA[task set failed]]></message>
<message mid="602"><![CDATA[non-existent task]]></message>
<message mid="603"><![CDATA[reach gold limit, unable to complete the task.]]></message>
<message mid="700"><![CDATA[chat error]]></message>
<message mid="800"><![CDATA[learn skills failed]]></message>
<message mid="801"><![CDATA[skills delete failed]]></message>
<message mid="802"><![CDATA[no such skills]]></message>
<message mid="803"><![CDATA[no such skills upgrade failed]]></message>
<message mid="804"><![CDATA[lack of skill points to upgrade failed]]></message>
<message mid="805"><![CDATA[Failed to upgrade the role of rating less than]]></message>
<message mid="806"><![CDATA[no further skills upgrading]]></message>
<message mid="900"><![CDATA[Unable to get friends list]]></message>
<message mid="901"><![CDATA[can not add friends group]]></message>
<message mid="902"><![CDATA[can not add friends]]></message>
<message mid="903"><![CDATA[already friends]]></message>
<message mid="904"><![CDATA[non-existent object]]></message>
<message mid="905"><![CDATA[object not friends]]></message>
<message mid="906"><![CDATA[non-existent group]]></message>
<message mid="907"><![CDATA[add friends failed]]></message>
<message mid="908"><![CDATA[Add Friends group failed]]></message>
<message mid="909"><![CDATA[delete friends failed]]></message>
<message mid="910"><![CDATA[delete friends group failed]]></message>
<message mid="515"><![CDATA[can not sell items]]></message>
<message mid="317"><![CDATA[team is already prepared to move the state to join the team]]></message>
<message mid="318"><![CDATA[In addition to the successful team members kicked]]></message>
<message mid="319"><![CDATA[team full]]></message>
<message mid="320"><![CDATA[can not join the team permanently removed]]></message>
<message mid="321"><![CDATA[not to join the team]]></message>
<message mid="322"><![CDATA[no name, can not generate team]]></message>
<message mid="323"><![CDATA[password error, can not generate team]]></message>
<message mid="324"><![CDATA[team control level is incorrect]]></message>
<message mid="325"><![CDATA[because of the role of rating limit can not be added to team up]]></message>
<message mid="326"><![CDATA[can not remove themselves]]></message>
<message mid="327"><![CDATA[Information revised team failed]]></message>
<message mid="328"><![CDATA[team's name is not correct, modify the team information failed.]]></message>
<message mid="114"><![CDATA[role name can not use special characters]]></message>
<message mid="10"><![CDATA[and the server connection is not smooth]]></message>
<message mid="329"><![CDATA[password error]]></message>
<message mid="330"><![CDATA[team control level is incorrect]]></message>
<message mid="331"><![CDATA[Xuanzhao team list failed .]]></message>
<message mid="516"><![CDATA[can not sell store items]]></message>
<message mid="517"><![CDATA[can not trade items]]></message>
<message mid="701"><![CDATA[There is no dialogue object]]></message>
<message mid="702"><![CDATA[unable to send their own secret language]]></message>
<message mid="807"><![CDATA[Invalid skill points]]></message>
<message mid="1100"><![CDATA[Build PvP room failed]]></message>
<message mid="1101"><![CDATA[existing PvP room]]></message>
<message mid="1102"><![CDATA[out of PvP room failed]]></message>
<message mid="1103"><![CDATA[can not find the PvP room]]></message>
<message mid="1104"><![CDATA[PvP room passwords do not match, unable to enter.]]></message>
<message mid="1105"><![CDATA[PvP room is full]]></message>
<message mid="1106"><![CDATA[PvP room into the failed]]></message>
<message mid="332"><![CDATA[level too low to enter the copy.]]></message>
<message mid="333"><![CDATA[lack of fatigue, lack of access copies.]]></message>
<message mid="412"><![CDATA[coat of arms of gem combination of success!]]></message>
<message mid="413"><![CDATA[synthetic gem success!]]></message>
<message mid="201"><![CDATA[You have entered the fatigue play time, can not get items and coins.]]></message>
<message mid="604"><![CDATA[You have entered the fatigue play time, could not accept and complete the task, until your total time off the assembly line for 5 hours, to return to normal, and for your health, please under as soon as possible line break.]]></message>
<message mid="415"><![CDATA[storage limit for the amount of their holdings.]]></message>
<message mid="416"><![CDATA[more than the amount that can be kept.]]></message>
<message mid="417"><![CDATA[remove maximum amount of storage.]]></message>
<message mid="418"><![CDATA[remove holding the amount can not exceed the maximum amount.]]></message>
<message mid="420"><![CDATA[the amount of excess.]]></message>
<message mid="519"><![CDATA[beyond the limits may be held, the transaction failed.]]></message>
<message mid="520"><![CDATA[beyond the limits may be held, sales failure.]]></message>
<message mid="950"><![CDATA[not an invitation to stop the player.]]></message>
<message mid="952"><![CDATA[invited players to prevent the state.]]></message>
<message mid="953"><![CDATA[Unblock fails.]]></message>
<message mid="951"><![CDATA[to prevent failure.]]></message>
<message mid="421"><![CDATA[breath of life is insufficient resurrection.]]></message>
<message mid="605"><![CDATA[task space.]]></message>
<message mid="606"><![CDATA[task space quickly filled.]]></message>
<message mid="521"><![CDATA[backpack space.]]></message>
<message mid="522"><![CDATA[remove holding the amount can not exceed the maximum amount.]]></message>
<message mid="434"><![CDATA[This article can not be destroyed.]]></message>
<message mid="334"><![CDATA[the other party are unable to accept the invitation.]]></message>
<message mid="523"><![CDATA[the other party are unable to accept the message.]]></message>
<message mid="524"><![CDATA[the other party are unable to accept gifts.]]></message>
<message mid="525"><![CDATA[the other party are unable to accept the invitation.]]></message>
<message mid="911"><![CDATA[can not append each other as friends.]]></message>
<message mid="1000"><![CDATA[Failed to join the Society.]]></message>
<message mid="1001"><![CDATA[has joined the Association.]]></message>
<message mid="1002"><![CDATA[Association name already exists]]></message>
<message mid="1003"><![CDATA[Failed to create the Society.]]></message>
<message mid="1004"><![CDATA[refused to join the Association.]]></message>
<message mid="1005"><![CDATA[Exit Association failed.]]></message>
<message mid="1006"><![CDATA[no permissions.]]></message>
<message mid="1007"><![CDATA[Society of Information amend failed.]]></message>
<message mid="1008"><![CDATA[Association member functions modify the failure.]]></message>
<message mid="1009"><![CDATA[Association member information changes failed.]]></message>
<message mid="1010"><![CDATA[Association does not exist.]]></message>
<message mid="1011"><![CDATA[Association member does not exist.]]></message>
<message mid="1012"><![CDATA[Association president does not exist.]]></message>
<message mid="1013"><![CDATA[only the President of the Institute have permission.]]></message>
<message mid="1014"><![CDATA[Association president can not perform.]]></message>
<message mid="1015"><![CDATA[the user does not exist.]]></message>
<message mid="1016"><![CDATA[has joined the Association.]]></message>
<message mid="1017"><![CDATA[refused Association invited.]]></message>
<message mid="1018"><![CDATA[not in the same Association.]]></message>
<message mid="1019"><![CDATA[can not invite themselves.]]></message>
<message mid="1020"><![CDATA[can not expel its own.]]></message>
<message mid="1021"><![CDATA[This account has joined the Society.]]></message>
<message mid="1022"><![CDATA[Association of insufficient points.]]></message>
<message mid="1023"><![CDATA[Association points over.]]></message>
<message mid="1024"><![CDATA[Athletic Association of insufficient points.]]></message>
<message mid="1025"><![CDATA[Association actually over technical points.]]></message>
<message mid="1026"><![CDATA[Association of insufficient funds.]]></message>
<message mid="1027"><![CDATA[Association of the excess funds.]]></message>
<message mid="1028"><![CDATA[no member of the Association.]]></message>
<message mid="1029"><![CDATA[can not reduce the association level.]]></message>
<message mid="1030"><![CDATA[can not enhance the association level.]]></message>
<message mid="1031"><![CDATA[Association members can not reduce the ceiling.]]></message>
<message mid="1032"><![CDATA[Association members can not increase the limit.]]></message>
<message mid="1033"><![CDATA[member of the Association can not accept.]]></message>
<message mid="1034"><![CDATA[Association of dissolution of the failed (empty the Association funds )]]></message>
<message mid="1035"><![CDATA[Association of dissolution of the failed (empty the Association of Storage )]]></message>
<message mid="1036"><![CDATA[Association of dissolution of the failure (see expulsion of all Association members )]]></message>
<message mid="1037"><![CDATA[Association member registration failed.]]></message>
<message mid="1038"><![CDATA[The Society has disbanded.]]></message>
<message mid="1039"><![CDATA[Association of abnormal changes of information.]]></message>
<message mid="1040"><![CDATA[Society of Information amend failed.]]></message>
<message mid="1041"><![CDATA[Association member information changes exception.]]></message>
<message mid="1042"><![CDATA[Association member information changes failed.]]></message>
<message mid="1043"><![CDATA[server does not exist within the Association.]]></message>
<message mid="1044"><![CDATA[server does not exist within the membership of the Association.]]></message>
<message mid="1045"><![CDATA[User has joined the Association.]]></message>
<message mid="1046"><![CDATA[Association understaffed.]]></message>
<message mid="1047"><![CDATA[the lack of gold]]></message>
<message mid="1048"><![CDATA[Association of insufficient funds.]]></message>
<message mid="1049"><![CDATA[Association of warehouse to create enough cost.]]></message>
<message mid="1050"><![CDATA[Association of upgrade failure.]]></message>
<message mid="1051"><![CDATA[not reached the level to create the Society.]]></message>
<message mid="1052"><![CDATA[increase the cap member of the Association request failed.]]></message>
<message mid="1053"><![CDATA[There are Association members.]]></message>
<message mid="118"><![CDATA[can not be removed as President of the Institute's figures.]]></message>
<message mid="1200"><![CDATA[Ok]]></message>
<message mid="1201"><![CDATA[success]]></message>
<message mid="1202"><![CDATA[Communication parameter error.]]></message>
<message mid="1203"><![CDATA[the modules have been initialized.]]></message>
<message mid="1204"><![CDATA[the modules are not initialized.]]></message>
<message mid="1205"><![CDATA[module failed to initialize.]]></message>
<message mid="1206"><![CDATA[connection pool build failure.]]></message>
<message mid="1207"><![CDATA[get connection failed.]]></message>
<message mid="1208"><![CDATA[open connection failed.]]></message>
<message mid="1209"><![CDATA[Sending failed.]]></message>
<message mid="1210"><![CDATA[receiver failure.]]></message>
<message mid="1211"><![CDATA[authentication server return value of the error.]]></message>
<message mid="1212"><![CDATA[certification string error.]]></message>
<message mid="1213"><![CDATA[an error occurred can not be expected.]]></message>
<message mid="1214"><![CDATA[authentication server to convey the parameter is incorrect.]]></message>
<message mid="1215"><![CDATA[IP address error.]]></message>
<message mid="1216"><![CDATA[user account error.]]></message>
<message mid="1217"><![CDATA[user password.]]></message>
<message mid="1218"><![CDATA[password wrong more than the number of restrictions.]]></message>
<message mid="1219"><![CDATA[the user does not exist.]]></message>
<message mid="1220"><![CDATA[authentication server system error occurred.]]></message>
<message mid="1221"><![CDATA[cookie error.]]></message>
<message mid="1222"><![CDATA[cookie does not exist.]]></message>
<message mid="1223"><![CDATA[cookie complete.]]></message>
<message mid="526"><![CDATA[is not yet equipped items.]]></message>
<message mid="527"><![CDATA[This article can not be equipped.]]></message>
<message mid="1300"><![CDATA[confirm authentication information when an error occurs.]]></message>
<message mid="1301"><![CDATA[confirm authentication information when an error occurs.]]></message>
<message mid="1302"><![CDATA[confirm authentication information when an error occurs.]]></message>
<message mid="1303"><![CDATA[specify the authentication information when the error occurred.]]></message>
<message mid="1304"><![CDATA[confirm authentication information when an error occurs.]]></message>
<message mid="1305"><![CDATA[confirm authentication information when an error occurs.]]></message>
<message mid="1306"><![CDATA[specify the authentication information when the error occurred.]]></message>
<message mid="1307"><![CDATA[specify the authentication information when the error occurred.]]></message>
<message mid="1308"><![CDATA[confirm authentication information when an error occurs.]]></message>
<message mid="1309"><![CDATA[confirm authentication information when an error occurs.]]></message>
<message mid="1310"><![CDATA[confirm authentication information when an error occurs.]]></message>
<message mid="100101"><![CDATA[General error occurred.]]></message>
<message mid="100102"><![CDATA[General error occurred.]]></message>
<message mid="100103"><![CDATA[General error occurred.]]></message>
<message mid="100104"><![CDATA[General error occurred.]]></message>
<message mid="100105"><![CDATA[role does not exist.]]></message>
<message mid="100106"><![CDATA[CheckFirstVillage value has been updated to 1.]]></message>
<message mid="101101"><![CDATA[login account has been registered.]]></message>
<message mid="101102"><![CDATA[account does not exist. (Internal account )]]></message>
<message mid="101103"><![CDATA[and the shield to retain the existing duplicate IP range.]]></message>
<message mid="101104"><![CDATA[have shielding or shielding the IP range ban.]]></message>
<message mid="101105"><![CDATA[mask IP range does not exist.]]></message>
<message mid="101106"><![CDATA[Shield reserves the IP range does not exist.]]></message>
<message mid="101107"><![CDATA[temporary shielding zone does not exist.]]></message>
<message mid="101108"><![CDATA[ban log interval.]]></message>
<message mid="101109"><![CDATA[ban logged IP.]]></message>
<message mid="101110"><![CDATA[password inconsistent.]]></message>
<message mid="101111"><![CDATA[is not blocked account.]]></message>
<message mid="101112"><![CDATA[the role is not blocked.]]></message>
<message mid="101113"><![CDATA[No action.]]></message>
<message mid="101114"><![CDATA[beyond the maximum number of character creation. Today can not continue to create the role.]]></message>
<message mid="101115"><![CDATA[account does not exist.]]></message>
<message mid="101116"><![CDATA[role name already exists]]></message>
<message mid="101117"><![CDATA[role does not exist.]]></message>
<message mid="101118"><![CDATA[The role has been deleted.]]></message>
<message mid="101119"><![CDATA[beyond the role can have the greatest number.]]></message>
<message mid="101120"><![CDATA[no title records.]]></message>
<message mid="101121"><![CDATA[no title records can be modified.]]></message>
<message mid="101122"><![CDATA[Sesion ID inconsistent.]]></message>
<message mid="101123"><![CDATA[There can be no lifting of sanctions.]]></message>
<message mid="101124"><![CDATA[the contents of the sanctions had been lifted.]]></message>
<message mid="101125"><![CDATA[beyond the 2 limit the number of authentication failure.]]></message>
<message mid="101126"><![CDATA[and before the 2 inconsistent authentication code.]]></message>
<message mid="101127"><![CDATA[2 times inconsistent authentication code.]]></message>
<message mid="101128"><![CDATA[not set two passwords.]]></message>
<message mid="101129"><![CDATA[This account has been set to have the same kinds of sanctions.]]></message>
<message mid="101130"><![CDATA[The role of the set have the same kinds of sanctions.]]></message>
<message mid="101131"><![CDATA[General error occurred.]]></message>
<message mid="101132"><![CDATA[waiting ranks have been included in the account.]]></message>
<message mid="101133"><![CDATA[wait for the ranks is empty.]]></message>
<message mid="101134"><![CDATA[waiting for does not exist in the ranks of the role.]]></message>
<message mid="101135"><![CDATA[waiting for a request to delete the account the ranks of the actual deletion of the account number and the number of inconsistencies.]]></message>
<message mid="101136"><![CDATA[insufficient funds.]]></message>
<message mid="101142"><![CDATA[The server can not create more roles.]]></message>
<message mid="101137"><![CDATA[OBT activity repeated with long currency issuance, delete.]]></message>
<message mid="101138"><![CDATA[OBT activities with the dragon coins issued failed.]]></message>
<message mid="101139"><![CDATA[beyond the prohibition of authentication prompts 2nd time.]]></message>
<message mid="101140"><![CDATA[General error occurred.]]></message>
<message mid="101141"><![CDATA[only Pioneer player can log on.]]></message>
<message mid="102101"><![CDATA[superior because of sanctions does not exist.]]></message>
<message mid="102102"><![CDATA[the reasons for lower levels of sanctions does not exist.]]></message>
<message mid="102103"><![CDATA[there is no reason to remove the sanctions.]]></message>
<message mid="102104"><![CDATA[lower sanctions because there can not be deleted.]]></message>
<message mid="102105"><![CDATA[because of sanctions does not exist.]]></message>
<message mid="102106"><![CDATA[UsedFlag has been updated to 1.]]></message>
<message mid="102107"><![CDATA[because of sanctions already in use. Not be deleted.]]></message>
<message mid="102108"><![CDATA[have used version of the patch.]]></message>
<message mid="102109"><![CDATA[no patch records.]]></message>
<message mid="103101"><![CDATA[the role of president for the public. Not be deleted.]]></message>
<message mid="103102"><![CDATA[role does not exist.]]></message>
<message mid="103103"><![CDATA[General error occurred.]]></message>
<message mid="103104"><![CDATA[the role of skills has been reset.]]></message>
<message mid="103105"><![CDATA[skills as the initial state. Can not reset the contents.]]></message>
<message mid="103106"><![CDATA[transfer before and after the same job code.]]></message>
<message mid="103107"><![CDATA[shortcut bar does not exist.]]></message>
<message mid="103108"><![CDATA[prompt does not exist.]]></message>
<message mid="103109"><![CDATA[no copy has been completed.]]></message>
<message mid="103110"><![CDATA[The copy has not been completed.]]></message>
<message mid="103111"><![CDATA[no additional capacity to value.]]></message>
<message mid="103112"><![CDATA[no additional attributes.]]></message>
<message mid="103113"><![CDATA[has received the title.]]></message>
<message mid="103114"><![CDATA[have added the action]]></message>
<message mid="103115"><![CDATA[No action.]]></message>
<message mid="103116"><![CDATA[no task.]]></message>
<message mid="103117"><![CDATA[no taskbar, or other tasks have been replaced.]]></message>
<message mid="103118"><![CDATA[have added tasks.]]></message>
<message mid="103119"><![CDATA[General error occurred.]]></message>
<message mid="103120"><![CDATA[General error occurred.]]></message>
<message mid="103121"><![CDATA[has completed the task.]]></message>
<message mid="103122"><![CDATA[General error occurred.]]></message>
<message mid="103123"><![CDATA[game currency shortage.]]></message>
<message mid="103124"><![CDATA[warehouse game currency shortage.]]></message>
<message mid="103125"><![CDATA[the mission has been completed.]]></message>
<message mid="103126"><![CDATA[General error occurred.]]></message>
<message mid="103127"><![CDATA[does not meet the requirements of daily, weekly mission.]]></message>
<message mid="103128"><![CDATA[beyond the friends group to create the ceiling.]]></message>
<message mid="103129"><![CDATA[beyond the maximum number of friends.]]></message>
<message mid="103130"><![CDATA[no friends group.]]></message>
<message mid="103131"><![CDATA[no role can be added as friends.]]></message>
<message mid="103132"><![CDATA[Unable to object to add as a friend.]]></message>
<message mid="103133"><![CDATA[no friends role.]]></message>
<message mid="103134"><![CDATA[The role has been added as friends.]]></message>
<message mid="103135"><![CDATA[request to delete the Friends of the volume and the actual number of friends to remove inconsistencies.]]></message>
<message mid="103136"><![CDATA[friends group of friends request to change the number and the number of inconsistencies in the actual change friends.]]></message>
<message mid="103137"><![CDATA[want to shield the object does not exist.]]></message>
<message mid="103138"><![CDATA[can not shield operating personnel.]]></message>
<message mid="103139"><![CDATA[have shield role.]]></message>
<message mid="103140"><![CDATA[the request to lift the role of shielding the volume and the actual lifting of the role of shielding the number of inconsistencies.]]></message>
<message mid="103141"><![CDATA[no shielding role.]]></message>
<message mid="103142"><![CDATA[no professional record.]]></message>
<message mid="103143"><![CDATA[have added skills.]]></message>
<message mid="103144"><![CDATA[skill does not exist.]]></message>
<message mid="103145"><![CDATA[lack of skill points.]]></message>
<message mid="103146"><![CDATA[no skills.]]></message>
<message mid="103147"><![CDATA[General error occurred.]]></message>
<message mid="103148"><![CDATA[the role of gifts does not exist.]]></message>
<message mid="103149"><![CDATA[General error occurred.]]></message>
<message mid="103150"><![CDATA[General error occurred.]]></message>
<message mid="103151"><![CDATA[item does not exist.]]></message>
<message mid="103152"><![CDATA[General error occurred.]]></message>
<message mid="103153"><![CDATA[intensive goods does not exist.]]></message>
<message mid="103154"><![CDATA[hardening material goods does not exist.]]></message>
<message mid="103155"><![CDATA[General error occurred.]]></message>
<message mid="103156"><![CDATA[General error occurred.]]></message>
<message mid="103157"><![CDATA[need to modify the detailed properties of the daily, weekly mission does not exist.]]></message>
<message mid="103158"><![CDATA[no cash resurrection currency.]]></message>
<message mid="103159"><![CDATA[General error occurred.]]></message>
<message mid="103160"><![CDATA[before and after the position change of the same items.]]></message>
<message mid="103161"><![CDATA[additional items of information is not correct.]]></message>
<message mid="103162"><![CDATA[written role does not exist.]]></message>
<message mid="103163"><![CDATA[the role of receipt of the letter does not exist.]]></message>
<message mid="103164"><![CDATA[unable to send a message to the GM.]]></message>
<message mid="103165"><![CDATA[did not receive the message.]]></message>
<message mid="103166"><![CDATA[e-mail does not exist.]]></message>
<message mid="103167"><![CDATA[no additional gold.]]></message>
<message mid="103168"><![CDATA[no additional items.]]></message>
<message mid="103169"><![CDATA[beyond no one can register stores the number of items.]]></message>
<message mid="103170"><![CDATA[item does not exist or insufficient number of items.]]></message>
<message mid="103171"><![CDATA[does not meet the conditions of the items.]]></message>
<message mid="103172"><![CDATA[not to store items no.]]></message>
<message mid="103173"><![CDATA[No one store does not exist in the items can be de-registration.]]></message>
<message mid="103174"><![CDATA[items have been sold]]></message>
<message mid="103175"><![CDATA[unregistered items.]]></message>
<message mid="103176"><![CDATA[no items can be settled.]]></message>
<message mid="103177"><![CDATA[no added activities.]]></message>
<message mid="103178"><![CDATA[two items of location information is not correct.]]></message>
<message mid="103179"><![CDATA[General error occurred.]]></message>
<message mid="103180"><![CDATA[General error occurred.]]></message>
<message mid="103181"><![CDATA[General error occurred.]]></message>
<message mid="103182"><![CDATA[General error occurred.]]></message>
<message mid="103183"><![CDATA[the same item.]]></message>
<message mid="103184"><![CDATA[General error occurred.]]></message>
<message mid="103185"><![CDATA[role name has been registered.]]></message>
<message mid="103186"><![CDATA[beyond the store every week no one can register in the number of items.]]></message>
<message mid="103187"><![CDATA[no effect items.]]></message>
<message mid="442"><![CDATA[resurrection of the book can have up to 50.]]></message>
<message mid="101143"><![CDATA[role does not exist.]]></message>
<message mid="101144"><![CDATA[General error occurred.]]></message>
<message mid="101145"><![CDATA[buy items of information does not exist.]]></message>
<message mid="101146"><![CDATA[Dragon currency deposit / remove the information does not exist.]]></message>
<message mid="101147"><![CDATA[limited edition merchandise, more than to buy a limited number.]]></message>
<message mid="102110"><![CDATA[record does not exist. [GMServerState]]]></message>
<message mid="102111"><![CDATA[record does not exist. [GMCopyLog]]]></message>
<message mid="103188"><![CDATA[no actual goods to be exchanged.]]></message>
<message mid="103189"><![CDATA[role does not exist or have been removed over the waiting time, the role can not be removed resurrection.]]></message>
<message mid="1400"><![CDATA[Internet cafe is not the theme activities, please contact the Internet cafe administrator.]]></message>
<message mid="1401"><![CDATA[concessions and active content (difficult to demonstrate activities of publicity pictures, plain text display )]]></message>
<message mid="1402"><![CDATA[Internet cafe point deduction due to the end of game time, please consult Internet cafe administrator.]]></message>
<message mid="1403"><![CDATA[Internet cafes will be deducted when the time expires the end of the game, please contact Internet cafe administrator.]]></message>
<message mid="1404"><![CDATA[over IP allows the connection, please contact the Internet cafe administrator.]]></message>
<message mid="1405"><![CDATA[you are not active object cafes, please contact customer service grand cafes.]]></message>
<message mid="1406"><![CDATA[Internet cafe features the current error, please try again later.]]></message>
<message mid="1410"><![CDATA[an error.]]></message>
<message mid="1411"><![CDATA[an error.]]></message>
<message mid="1412"><![CDATA[an error.]]></message>
<message mid="1413"><![CDATA[repeat purchase your product.]]></message>
<message mid="1414"><![CDATA[has exceeded the total number of goods can be purchased.]]></message>
<message mid="1415"><![CDATA[has exceeded the number of goods purchased.]]></message>
<message mid="1416"><![CDATA[not to re-purchase date.]]></message>
<message mid="1417"><![CDATA[an error.]]></message>
<message mid="1418"><![CDATA[an error.]]></message>
<message mid="1419"><![CDATA[an error.]]></message>
<message mid="1420"><![CDATA[the game is limited.]]></message>
<message mid="1421"><![CDATA[This is not to purchase goods.]]></message>
<message mid="1422"><![CDATA[limited, can not buy.]]></message>
<message mid="1423"><![CDATA[re-order period has not yet ended, so can not buy.]]></message>
<message mid="1424"><![CDATA[related goods can not be sent as a gift.]]></message>
<message mid="1425"><![CDATA[Order quantity is limited (the recipient )]]></message>
<message mid="1426"><![CDATA[is not re-ordering of the time (the recipient )]]></message>
<message mid="1427"><![CDATA[This function can not be settled.]]></message>
<message mid="1428"><![CDATA[have used coupons.]]></message>
<message mid="1429"><![CDATA[can not use coupons.]]></message>
<message mid="1430"><![CDATA[Cancel coupons (user expiration )]]></message>
<message mid="1431"><![CDATA[coupon error, can not be used.]]></message>
<message mid="1432"><![CDATA[Coupon No input errors.]]></message>
<message mid="1433"><![CDATA[is not this game can use coupons.]]></message>
<message mid="1434"><![CDATA[has expired coupons.]]></message>
<message mid="1435"><![CDATA[is the other coupons can not be used.]]></message>
<message mid="1436"><![CDATA[beyond the limited number of coupons used.]]></message>
<message mid="1437"><![CDATA[limiting the number of coupons to use input failure.]]></message>
<message mid="1438"><![CDATA[Internet cafe Internet cafe dedicated coupon can only use the coupons can be used.]]></message>
<message mid="1439"><![CDATA[Internet cafe Internet cafe dedicated coupon can only use the coupons have been used.]]></message>
<message mid="1440"><![CDATA[Internet cafe Internet cafe dedicated coupon can only use the coupon has expired.]]></message>
<message mid="1441"><![CDATA[Internet cafe Internet cafe dedicated coupon can only use the coupon is stopped issuing coupons.]]></message>
<message mid="1442"><![CDATA[now can not use coupons, please try again later.]]></message>
<message mid="1443"><![CDATA[over the limit as a gift can not be sent.]]></message>
<message mid="1444"><![CDATA[subject to the age of gifts to send.]]></message>
<message mid="1445"><![CDATA[limited and can not send a gift to send.]]></message>
<message mid="1446"><![CDATA[to limit players to receive gifts, not gifts.]]></message>
<message mid="1447"><![CDATA[related articles over the purchase limit.]]></message>
<message mid="1448"><![CDATA[can not use the grand point of coupons. Go to the big game platform, point coupons related functions to modify the relevant settings menu.]]></message>
<message mid="1449"><![CDATA[user account is locked.]]></message>
<message mid="1450"><![CDATA[The role does not exist.]]></message>
<message mid="1451"><![CDATA[insufficient funds can not buy.]]></message>
<message mid="1452"><![CDATA[the amount of recharge over the use period and can not be used.]]></message>
<message mid="1453"><![CDATA[This article can not be purchased.]]></message>
<message mid="1454"><![CDATA[The player is limited to purchase.]]></message>
<message mid="446"><![CDATA[ticket items at the point of the window can not drag and drop items.]]></message>
<message mid="531"><![CDATA[to expand the number of vacancies is less than the current expansion of the number of purchases of goods.]]></message>
<message mid="532"><![CDATA[insufficient funds.]]></message>
<message mid="533"><![CDATA[was purchased was an error. Goods will be issued after the re-login.]]></message>
<message mid="12"><![CDATA[an error occurred Hackshield related. Please contact Simon customer service. (TEL 02-2186-3000 / hs@ahnlab.com )]]></message>
<message mid="115"><![CDATA[the system is not certified to judge your account, please pwd.sdo.com website information to bill the forgotten anti-addicted]]></message>
<message mid="339"><![CDATA[Search the destination does not exist.]]></message>
<message mid="534"><![CDATA[not to their own gifts.]]></message>
<message mid="535"><![CDATA[backpack is full, can not accept gifts.]]></message>
<message mid="536"><![CDATA[warehouse is full and can not accept gifts.]]></message>
<message mid="537"><![CDATA[beyond the resurrection of the book holdings limited, can not accept gifts.]]></message>
<message mid="528"><![CDATA[Dragon currency shortage.]]></message>
<message mid="529"><![CDATA[Dragon currency can not buy goods.]]></message>
<message mid="530"><![CDATA[in the mall can not leave the open state.]]></message>
<message mid="538"><![CDATA[not as a gift item.]]></message>
<message mid="1407"><![CDATA[can not log on. Please contact Customer Service NEXON.]]></message>
<message mid="202"><![CDATA[data are included in their role.]]></message>
<message mid="203"><![CDATA[the other role of the data is loaded.]]></message>
<message mid="116"><![CDATA[Your account is now in a minor state, a reasonable allocation of the appropriate game time!]]></message>
<message mid="542"><![CDATA[now unable to purchase the product. Please refer to the official website.]]></message>
<message mid="340"><![CDATA[invitation to failure. Make sure that channel.]]></message>
<message mid="341"><![CDATA[can not invite ready to role.]]></message>
<message mid="544"><![CDATA[VIP level insufficient to purchase.]]></message>
<message mid="449"><![CDATA[clothing synthesis failed.]]></message>
<message mid="450"><![CDATA[synthetic materials information is inconsistent with the synthesis of information, synthesis has been canceled.]]></message>
<message mid="451"><![CDATA[synthetics or quantity.]]></message>
<message mid="452"><![CDATA[Can not open synthesis window.]]></message>
<message mid="453"><![CDATA[can not close the synthesis window.]]></message>
<message mid="454"><![CDATA[synthetic materials and synthesis of information inconsistent with the results, synthetic has been canceled.]]></message>
<message mid="455"><![CDATA[ability to choose the value of information is inconsistent with the synthesis of information, synthesis has been canceled.]]></message>
</messages>
